pyrad/__init__.py
pyrad/bidict.py
pyrad/client.py
pyrad/client_async.py
pyrad/curved.py
pyrad/dictfile.py
pyrad/dictionary.py
pyrad/host.py
pyrad/packet.py
pyrad/proxy.py
pyrad/server.py
pyrad/server_async.py
pyrad/tools.py
pyrad-2.4.dist-info/LICENSE.txt
pyrad-2.4.dist-info/METADATA
pyrad-2.4.dist-info/WHEEL
pyrad-2.4.dist-info/top_level.txt
pyrad-2.4.dist-info/zip-safe
pyrad-2.4.dist-info/RECORD
