Metadata-Version: 1.1
Name: pyrad
Version: 2.4
Summary: RADIUS tools
Home-page: https://github.com/pyradius/pyrad
Author: Istvan Ruzman, Christian Giese
Author-email: istvan@ruzman.eu, developer@gicnet.de
License: BSD
Keywords: radius,authentication
Platform: UNKNOWN
Classifier: Development Status :: 6 - Mature
Classifier: Intended Audience :: Developers
Classifier: License :: OSI Approved :: BSD License
Classifier: Programming Language :: Python :: 2.7
Classifier: Programming Language :: Python :: 3.6
Classifier: Programming Language :: Python :: 3.7
Classifier: Programming Language :: Python :: 3.8
Classifier: Topic :: Software Development :: Libraries :: Python Modules
Classifier: Topic :: System :: Systems Administration :: Authentication/Directory
